{"status":"done","publicPath":"http://0.0.0.0:8080/","chunks":{"app":[{"name":"__assets_front_control/js/app.js","publicPath":"http://0.0.0.0:8080/__assets_front_control/js/app.js","path":"/home/adder/proyectos_trabajo/control_productos_CC/front_control/out_front_control/__assets_front_control/js/app.js"},{"name":"app.a165e051c16f249750d0.hot-update.js","publicPath":"http://0.0.0.0:8080/app.a165e051c16f249750d0.hot-update.js","path":"/home/adder/proyectos_trabajo/control_productos_CC/front_control/out_front_control/app.a165e051c16f249750d0.hot-update.js"}]},"error":"ModuleError","message":"Module Error (from ./node_modules/eslint-loader/index.js):\nerror: Parsing error: missing-whitespace-between-attributes (vue/no-parsing-error) at src/components/productos/ListaProductos.vue:22:87:\n  20 |                 <div class=\"ui two buttons\">\n  21 |                     <div class=\"ui editar button\">Editar</div>\n> 22 |                     <div class=\"ui orange button\" @click=\"eliminar_producto(producto)\"\">Eliminar</div>\n     |                                                                                       ^\n  23 |                 </div>\n  24 |                 </div>\n  25 |             </div>\n\n\nerror: Parsing error: unexpected-character-in-attribute-name (vue/no-parsing-error) at src/components/productos/ListaProductos.vue:22:87:\n  20 |                 <div class=\"ui two buttons\">\n  21 |                     <div class=\"ui editar button\">Editar</div>\n> 22 |                     <div class=\"ui orange button\" @click=\"eliminar_producto(producto)\"\">Eliminar</div>\n     |                                                                                       ^\n  23 |                 </div>\n  24 |                 </div>\n  25 |             </div>\n\n\n2 errors found."}